ez_setup.py
setup.py
setuptools-0.6c9-py2.5.egg
EntityStore.egg-info/PKG-INFO
EntityStore.egg-info/SOURCES.txt
EntityStore.egg-info/dependency_links.txt
EntityStore.egg-info/requires.txt
EntityStore.egg-info/top_level.txt
entitystore/__init__.py
entitystore/entityconfig.py
entitystore/handlers.py
entitystore/model.py
entitystore/storemanager.py
entitystore/workercontrol.py