Metadata-Version: 1.0
Name: EntityStore
Version: 0.3.6
Summary: EntityStore - REST interface for CRUD on (RDF) Entities.
Home-page: UNKNOWN
Author: Ben O'Steen
Author-email: bosteen@gmail.com
License: UNKNOWN
Platform: UNKNOWN
